nexpy/__init__.py
nexpy/_version.py
nexpy/default.py
nexpy/py.typed
nexpy/x_function.py
nexpy/x_one_way_function.py
nexpy/core/__init__.py
nexpy/core/auxiliary/__init__.py
nexpy/core/auxiliary/listenable_mixin.py
nexpy/core/auxiliary/listenable_protocol.py
nexpy/core/auxiliary/utils.py
nexpy/core/auxiliary/weak_reference_storage.py
nexpy/core/hooks/__init__.py
nexpy/core/hooks/hook_aliases.py
nexpy/core/hooks/foundation/__init__.py
nexpy/core/hooks/foundation/hook_base.py
nexpy/core/hooks/implementations/__init__.py
nexpy/core/hooks/implementations/floating_hook.py
nexpy/core/hooks/implementations/owned_read_only_hook.py
nexpy/core/hooks/implementations/owned_writable_hook.py
nexpy/core/hooks/mixins/__init__.py
nexpy/core/hooks/mixins/hook_with_isolated_validation_mixin.py
nexpy/core/hooks/mixins/hook_with_owner_mixin.py
nexpy/core/hooks/mixins/hook_with_reaction_mixin.py
nexpy/core/hooks/mixins/hook_with_setter_mixin.py
nexpy/core/hooks/protocols/__init__.py
nexpy/core/hooks/protocols/hook_protocol.py
nexpy/core/hooks/protocols/isolated_validatable_hook_protocol.py
nexpy/core/hooks/protocols/owned_hook_protocol.py
nexpy/core/hooks/protocols/reactive_hook_protocol.py
nexpy/core/hooks/protocols/writable_hook_protocol.py
nexpy/core/nexus_system/__init__.py
nexpy/core/nexus_system/default_nexus_manager.py
nexpy/core/nexus_system/nexus.py
nexpy/core/nexus_system/nexus_manager.py
nexpy/core/nexus_system/submission_error.py
nexpy/core/nexus_system/system_analysis.py
nexpy/core/nexus_system/update_function_values.py
nexpy/core/nexus_system/internal_submit_methods/__init__.py
nexpy/core/nexus_system/internal_submit_methods/helper_methods.py
nexpy/core/nexus_system/internal_submit_methods/internal_submit_1.py
nexpy/core/nexus_system/internal_submit_methods/internal_submit_2.py
nexpy/core/nexus_system/internal_submit_methods/internal_submit_3.py
nexpy/core/publisher_subscriber/__init__.py
nexpy/core/publisher_subscriber/publisher_mixin.py
nexpylib-0.6.0.dist-info/licenses/LICENSE
nexpylib-0.6.0.dist-info/METADATA
nexpylib-0.6.0.dist-info/WHEEL
nexpylib-0.6.0.dist-info/top_level.txt
nexpylib-0.6.0.dist-info/RECORD
