Metadata-Version: 2.4
Name: nexpylib
Version: 0.6.0
Summary: Transitive synchronization and shared-state fusion for Python through Nexus fusion and atomic internal synchronization
Author-email: Benedikt Axel Brandes <benedikt.brandes@me.com>
Maintainer-email: Benedikt Axel Brandes <benedikt.brandes@me.com>
License: Apache-2.0
Project-URL: Homepage, https://github.com/babrandes/nexpylib
Project-URL: Documentation, https://nexpylib.readthedocs.io/
Project-URL: Repository, https://github.com/babrandes/nexpylib.git
Project-URL: Bug Tracker, https://github.com/babrandes/nexpylib/issues
Keywords: reactive,binding,data-binding,synchronization,nexus,fusion,observable,gui,reactive-programming
Classifier: Development Status :: 3 - Alpha
Classifier: Intended Audience :: Developers
Classifier: License :: OSI Approved :: Apache Software License
Classifier: Operating System :: OS Independent
Classifier: Programming Language :: Python :: 3.13
Classifier: Topic :: Software Development :: Libraries :: Python Modules
Classifier: Topic :: Software Development :: Libraries :: Application Frameworks
Classifier: Topic :: Software Development :: User Interfaces
Requires-Python: >=3.13
License-File: LICENSE
Requires-Dist: typing-extensions>=4.0.0
Provides-Extra: dev
Requires-Dist: pytest>=6.0; extra == "dev"
Requires-Dist: pytest-cov>=2.0; extra == "dev"
Requires-Dist: black>=21.0; extra == "dev"
Requires-Dist: flake8>=3.8; extra == "dev"
Requires-Dist: mypy>=0.800; extra == "dev"
Requires-Dist: pre-commit>=2.0; extra == "dev"
Provides-Extra: docs
Requires-Dist: sphinx>=4.0; extra == "docs"
Requires-Dist: sphinx-rtd-theme>=1.0; extra == "docs"
Requires-Dist: myst-parser>=0.15; extra == "docs"
Dynamic: license-file
